depgrep/__init__.py
depgrep/depgrep.py
depgrep-0.1.3.dist-info/LICENSE
depgrep-0.1.3.dist-info/METADATA
depgrep-0.1.3.dist-info/WHEEL
depgrep-0.1.3.dist-info/top_level.txt
depgrep-0.1.3.dist-info/RECORD
