Metadata-Version: 2.1
Name: depgrep
Version: 0.1.3
Summary: Dependency parse searching
Home-page: https://github.com/interrogator/depgrep
Author: Danny McDonald
Author-email: mcddjx@gmail.com
License: UNKNOWN
Keywords: linguistics nlp dependencies conll
Platform: UNKNOWN
Classifier: Topic :: Utilities
Requires-Python: >=3.6
Requires-Dist: pandas
Requires-Dist: pyparsing
Requires-Dist: nltk
